{"nodes": [{"id": "e_github_generativeai_rag_api_routers_hybrid_search_py", "label": "hybrid_search.py", "file_type": "code", "source_file": "api/routers/hybrid_search.py", "source_location": "L1"}, {"id": "e_github_generativeai_rag_api_routers_hybrid_search_hybrid_search", "label": "hybrid_search()", "file_type": "code", "source_file": "api/routers/hybrid_search.py", "source_location": "L15"}, {"id": "hybridsearchrequest", "label": "HybridSearchRequest", "file_type": "code", "source_file": "", "source_location": "", "origin_file": "E:\\GitHub\\GenerativeAI\\RAG\\api\\routers\\hybrid_search.py"}, {"id": "searchdep", "label": "SearchDep", "file_type": "code", "source_file": "", "source_location": "", "origin_file": "E:\\GitHub\\GenerativeAI\\RAG\\api\\routers\\hybrid_search.py"}, {"id": "embeddingsdep", "label": "EmbeddingsDep", "file_type": "code", "source_file": "", "source_location": "", "origin_file": "E:\\GitHub\\GenerativeAI\\RAG\\api\\routers\\hybrid_search.py"}, {"id": "searchresponse", "label": "SearchResponse", "file_type": "code", "source_file": "", "source_location": "", "origin_file": "E:\\GitHub\\GenerativeAI\\RAG\\api\\routers\\hybrid_search.py"}, {"id": "e_github_generativeai_rag_api_routers_hybrid_search_rationale_18", "label": "Hybrid search endpoint supporting multiple search modes.", "file_type": "rationale", "source_file": "api/routers/hybrid_search.py", "source_location": "L18"}], "edges": [{"source": "e_github_generativeai_rag_api_routers_hybrid_search_py", "target": "logging", "relation": "imports", "context": "import", "confidence": "EXTRACTED", "source_file": "api/routers/hybrid_search.py", "source_location": "L1", "weight": 1.0}, {"source": "e_github_generativeai_rag_api_routers_hybrid_search_py", "target": "time", "relation": "imports", "context": "import", "confidence": "EXTRACTED", "source_file": "api/routers/hybrid_search.py", "source_location": "L2", "weight": 1.0}, {"source": "e_github_generativeai_rag_api_routers_hybrid_search_py", "target": "fastapi", "relation": "imports_from", "context": "import", "confidence": "EXTRACTED", "source_file": "api/routers/hybrid_search.py", "source_location": "L4", "weight": 1.0}, {"source": "e_github_generativeai_rag_api_routers_hybrid_search_py", "target": "api_dependencies", "relation": "imports_from", "context": "import", "confidence": "EXTRACTED", "source_file": "api/routers/hybrid_search.py", "source_location": "L5", "weight": 1.0}, {"source": "e_github_generativeai_rag_api_routers_hybrid_search_py", "target": "api_metrics", "relation": "imports_from", "context": "import", "confidence": "EXTRACTED", "source_file": "api/routers/hybrid_search.py", "source_location": "L6", "weight": 1.0}, {"source": "e_github_generativeai_rag_api_routers_hybrid_search_py", "target": "api_schemas_api_search", "relation": "imports_from", "context": "import", "confidence": "EXTRACTED", "source_file": "api/routers/hybrid_search.py", "source_location": "L7", "weight": 1.0}, {"source": "e_github_generativeai_rag_api_routers_hybrid_search_py", "target": "e_github_generativeai_rag_api_routers_hybrid_search_hybrid_search", "relation": "contains", "confidence": "EXTRACTED", "source_file": "api/routers/hybrid_search.py", "source_location": "L15", "weight": 1.0}, {"source": "e_github_generativeai_rag_api_routers_hybrid_search_hybrid_search", "target": "hybridsearchrequest", "relation": "references", "context": "parameter_type", "confidence": "EXTRACTED", "source_file": "api/routers/hybrid_search.py", "source_location": "L15", "weight": 1.0}, {"source": "e_github_generativeai_rag_api_routers_hybrid_search_hybrid_search", "target": "searchdep", "relation": "references", "context": "parameter_type", "confidence": "EXTRACTED", "source_file": "api/routers/hybrid_search.py", "source_location": "L15", "weight": 1.0}, {"source": "e_github_generativeai_rag_api_routers_hybrid_search_hybrid_search", "target": "embeddingsdep", "relation": "references", "context": "parameter_type", "confidence": "EXTRACTED", "source_file": "api/routers/hybrid_search.py", "source_location": "L15", "weight": 1.0}, {"source": "e_github_generativeai_rag_api_routers_hybrid_search_hybrid_search", "target": "searchresponse", "relation": "references", "context": "return_type", "confidence": "EXTRACTED", "source_file": "api/routers/hybrid_search.py", "source_location": "L15", "weight": 1.0}, {"source": "e_github_generativeai_rag_api_routers_hybrid_search_hybrid_search", "target": "searchresponse", "relation": "calls", "context": "call", "confidence": "EXTRACTED", "source_file": "api/routers/hybrid_search.py", "source_location": "L69", "weight": 1.0}, {"source": "e_github_generativeai_rag_api_routers_hybrid_search_rationale_18", "target": "e_github_generativeai_rag_api_routers_hybrid_search_hybrid_search", "relation": "rationale_for", "confidence": "EXTRACTED", "source_file": "api/routers/hybrid_search.py", "source_location": "L18", "weight": 1.0}], "raw_calls": [{"caller_nid": "e_github_generativeai_rag_api_routers_hybrid_search_hybrid_search", "callee": "health_check", "is_member_call": true, "source_file": "E:\\GitHub\\GenerativeAI\\RAG\\api\\routers\\hybrid_search.py", "source_location": "L22", "receiver": "search_client"}, {"caller_nid": "e_github_generativeai_rag_api_routers_hybrid_search_hybrid_search", "callee": "HTTPException", "is_member_call": false, "source_file": "E:\\GitHub\\GenerativeAI\\RAG\\api\\routers\\hybrid_search.py", "source_location": "L23", "receiver": null}, {"caller_nid": "e_github_generativeai_rag_api_routers_hybrid_search_hybrid_search", "callee": "perf_counter", "is_member_call": true, "source_file": "E:\\GitHub\\GenerativeAI\\RAG\\api\\routers\\hybrid_search.py", "source_location": "L28", "receiver": "time"}, {"caller_nid": "e_github_generativeai_rag_api_routers_hybrid_search_hybrid_search", "callee": "embed_query", "is_member_call": true, "source_file": "E:\\GitHub\\GenerativeAI\\RAG\\api\\routers\\hybrid_search.py", "source_location": "L29", "receiver": "embeddings_service"}, {"caller_nid": "e_github_generativeai_rag_api_routers_hybrid_search_hybrid_search", "callee": "observe", "is_member_call": true, "source_file": "E:\\GitHub\\GenerativeAI\\RAG\\api\\routers\\hybrid_search.py", "source_location": "L30", "receiver": null}, {"caller_nid": "e_github_generativeai_rag_api_routers_hybrid_search_hybrid_search", "callee": "labels", "is_member_call": true, "source_file": "E:\\GitHub\\GenerativeAI\\RAG\\api\\routers\\hybrid_search.py", "source_location": "L30", "receiver": "EMBEDDING_LATENCY"}, {"caller_nid": "e_github_generativeai_rag_api_routers_hybrid_search_hybrid_search", "callee": "perf_counter", "is_member_call": true, "source_file": "E:\\GitHub\\GenerativeAI\\RAG\\api\\routers\\hybrid_search.py", "source_location": "L30", "receiver": "time"}, {"caller_nid": "e_github_generativeai_rag_api_routers_hybrid_search_hybrid_search", "callee": "info", "is_member_call": true, "source_file": "E:\\GitHub\\GenerativeAI\\RAG\\api\\routers\\hybrid_search.py", "source_location": "L31", "receiver": "logger"}, {"caller_nid": "e_github_generativeai_rag_api_routers_hybrid_search_hybrid_search", "callee": "warning", "is_member_call": true, "source_file": "E:\\GitHub\\GenerativeAI\\RAG\\api\\routers\\hybrid_search.py", "source_location": "L33", "receiver": "logger"}, {"caller_nid": "e_github_generativeai_rag_api_routers_hybrid_search_hybrid_search", "callee": "info", "is_member_call": true, "source_file": "E:\\GitHub\\GenerativeAI\\RAG\\api\\routers\\hybrid_search.py", "source_location": "L37", "receiver": "logger"}, {"caller_nid": "e_github_generativeai_rag_api_routers_hybrid_search_hybrid_search", "callee": "perf_counter", "is_member_call": true, "source_file": "E:\\GitHub\\GenerativeAI\\RAG\\api\\routers\\hybrid_search.py", "source_location": "L39", "receiver": "time"}, {"caller_nid": "e_github_generativeai_rag_api_routers_hybrid_search_hybrid_search", "callee": "search_unified", "is_member_call": true, "source_file": "E:\\GitHub\\GenerativeAI\\RAG\\api\\routers\\hybrid_search.py", "source_location": "L40", "receiver": "search_client"}, {"caller_nid": "e_github_generativeai_rag_api_routers_hybrid_search_hybrid_search", "callee": "observe", "is_member_call": true, "source_file": "E:\\GitHub\\GenerativeAI\\RAG\\api\\routers\\hybrid_search.py", "source_location": "L51", "receiver": null}, {"caller_nid": "e_github_generativeai_rag_api_routers_hybrid_search_hybrid_search", "callee": "labels", "is_member_call": true, "source_file": "E:\\GitHub\\GenerativeAI\\RAG\\api\\routers\\hybrid_search.py", "source_location": "L51", "receiver": "SEARCH_LATENCY"}, {"caller_nid": "e_github_generativeai_rag_api_routers_hybrid_search_hybrid_search", "callee": "perf_counter", "is_member_call": true, "source_file": "E:\\GitHub\\GenerativeAI\\RAG\\api\\routers\\hybrid_search.py", "source_location": "L51", "receiver": "time"}, {"caller_nid": "e_github_generativeai_rag_api_routers_hybrid_search_hybrid_search", "callee": "observe", "is_member_call": true, "source_file": "E:\\GitHub\\GenerativeAI\\RAG\\api\\routers\\hybrid_search.py", "source_location": "L52", "receiver": null}, {"caller_nid": "e_github_generativeai_rag_api_routers_hybrid_search_hybrid_search", "callee": "labels", "is_member_call": true, "source_file": "E:\\GitHub\\GenerativeAI\\RAG\\api\\routers\\hybrid_search.py", "source_location": "L52", "receiver": "SEARCH_RESULTS_COUNT"}, {"caller_nid": "e_github_generativeai_rag_api_routers_hybrid_search_hybrid_search", "callee": "get", "is_member_call": true, "source_file": "E:\\GitHub\\GenerativeAI\\RAG\\api\\routers\\hybrid_search.py", "source_location": "L52", "receiver": "results"}, {"caller_nid": "e_github_generativeai_rag_api_routers_hybrid_search_hybrid_search", "callee": "get", "is_member_call": true, "source_file": "E:\\GitHub\\GenerativeAI\\RAG\\api\\routers\\hybrid_search.py", "source_location": "L55", "receiver": "results"}, {"caller_nid": "e_github_generativeai_rag_api_routers_hybrid_search_hybrid_search", "callee": "append", "is_member_call": true, "source_file": "E:\\GitHub\\GenerativeAI\\RAG\\api\\routers\\hybrid_search.py", "source_location": "L56", "receiver": "hits"}, {"caller_nid": "e_github_generativeai_rag_api_routers_hybrid_search_hybrid_search", "callee": "SearchHit", "is_member_call": false, "source_file": "E:\\GitHub\\GenerativeAI\\RAG\\api\\routers\\hybrid_search.py", "source_location": "L57", "receiver": null}, {"caller_nid": "e_github_generativeai_rag_api_routers_hybrid_search_hybrid_search", "callee": "get", "is_member_call": true, "source_file": "E:\\GitHub\\GenerativeAI\\RAG\\api\\routers\\hybrid_search.py", "source_location": "L58", "receiver": "hit"}, {"caller_nid": "e_github_generativeai_rag_api_routers_hybrid_search_hybrid_search", "callee": "get", "is_member_call": true, "source_file": "E:\\GitHub\\GenerativeAI\\RAG\\api\\routers\\hybrid_search.py", "source_location": "L59", "receiver": "hit"}, {"caller_nid": "e_github_generativeai_rag_api_routers_hybrid_search_hybrid_search", "callee": "get", "is_member_call": true, "source_file": "E:\\GitHub\\GenerativeAI\\RAG\\api\\routers\\hybrid_search.py", "source_location": "L60", "receiver": "hit"}, {"caller_nid": "e_github_generativeai_rag_api_routers_hybrid_search_hybrid_search", "callee": "get", "is_member_call": true, "source_file": "E:\\GitHub\\GenerativeAI\\RAG\\api\\routers\\hybrid_search.py", "source_location": "L61", "receiver": "hit"}, {"caller_nid": "e_github_generativeai_rag_api_routers_hybrid_search_hybrid_search", "callee": "get", "is_member_call": true, "source_file": "E:\\GitHub\\GenerativeAI\\RAG\\api\\routers\\hybrid_search.py", "source_location": "L62", "receiver": "hit"}, {"caller_nid": "e_github_generativeai_rag_api_routers_hybrid_search_hybrid_search", "callee": "get", "is_member_call": true, "source_file": "E:\\GitHub\\GenerativeAI\\RAG\\api\\routers\\hybrid_search.py", "source_location": "L63", "receiver": "hit"}, {"caller_nid": "e_github_generativeai_rag_api_routers_hybrid_search_hybrid_search", "callee": "get", "is_member_call": true, "source_file": "E:\\GitHub\\GenerativeAI\\RAG\\api\\routers\\hybrid_search.py", "source_location": "L64", "receiver": "hit"}, {"caller_nid": "e_github_generativeai_rag_api_routers_hybrid_search_hybrid_search", "callee": "get", "is_member_call": true, "source_file": "E:\\GitHub\\GenerativeAI\\RAG\\api\\routers\\hybrid_search.py", "source_location": "L65", "receiver": "hit"}, {"caller_nid": "e_github_generativeai_rag_api_routers_hybrid_search_hybrid_search", "callee": "get", "is_member_call": true, "source_file": "E:\\GitHub\\GenerativeAI\\RAG\\api\\routers\\hybrid_search.py", "source_location": "L71", "receiver": "results"}, {"caller_nid": "e_github_generativeai_rag_api_routers_hybrid_search_hybrid_search", "callee": "info", "is_member_call": true, "source_file": "E:\\GitHub\\GenerativeAI\\RAG\\api\\routers\\hybrid_search.py", "source_location": "L78", "receiver": "logger"}, {"caller_nid": "e_github_generativeai_rag_api_routers_hybrid_search_hybrid_search", "callee": "error", "is_member_call": true, "source_file": "E:\\GitHub\\GenerativeAI\\RAG\\api\\routers\\hybrid_search.py", "source_location": "L84", "receiver": "logger"}, {"caller_nid": "e_github_generativeai_rag_api_routers_hybrid_search_hybrid_search", "callee": "HTTPException", "is_member_call": false, "source_file": "E:\\GitHub\\GenerativeAI\\RAG\\api\\routers\\hybrid_search.py", "source_location": "L85", "receiver": null}, {"caller_nid": "e_github_generativeai_rag_api_routers_hybrid_search_hybrid_search", "callee": "e", "is_member_call": false, "indirect": true, "context": "argument", "source_file": "E:\\GitHub\\GenerativeAI\\RAG\\api\\routers\\hybrid_search.py", "source_location": "L85"}], "callable_nids": ["e_github_generativeai_rag_api_routers_hybrid_search_hybrid_search"]}